{
  "north": -33.43239987967739,
  "south": -33.445041448573086,
  "east": -70.53755373467156,
  "west": -70.55459112633416,
  "trees": [
    {
      "lat": -33.435074,
      "lng": -70.547943,
      "meta": {
        "source": "arbocensus",
        "id": 410
      }
    },
    {
      "lat": -33.437408,
      "lng": -70.548549,
      "meta": {
        "source": "arbocensus",
        "id": 422
      }
    },
    {
      "lat": -33.4346931,
      "lng": -70.5479327,
      "meta": {
        "source": "arbocensus",
        "id": 397
      }
    },
    {
      "lat": -33.435734,
      "lng": -70.548038,
      "meta": {
        "source": "arbocensus",
        "id": 413
      }
    },
    {
      "lat": -33.434949,
      "lng": -70.547912,
      "meta": {
        "source": "arbocensus",
        "id": 405
      }
    },
    {
      "lat": -33.435798,
      "lng": -70.548019,
      "meta": {
        "source": "arbocensus",
        "id": 415
      }
    },
    {
      "lat": -33.436511,
      "lng": -70.54822,
      "meta": {
        "source": "arbocensus",
        "id": 419
      }
    },
    {
      "lat": -33.43481,
      "lng": -70.547815,
      "meta": {
        "source": "arbocensus",
        "id": 402
      }
    },
    {
      "lat": -33.4347125,
      "lng": -70.54811,
      "meta": {
        "source": "arbocensus",
        "id": 400
      }
    },
    {
      "lat": -33.43630900673294,
      "lng": -70.5444606219089,
      "meta": {
        "source": "arbocensus",
        "id": 520
      }
    },
    {
      "lat": -33.436030942743116,
      "lng": -70.54453323224114,
      "meta": {
        "source": "arbocensus",
        "id": 521
      }
    },
    {
      "lat": -33.434610713182956,
      "lng": -70.5456120562931,
      "meta": {
        "source": "arbocensus",
        "id": 527
      }
    },
    {
      "lat": -33.43604010352572,
      "lng": -70.54493965960117,
      "meta": {
        "source": "arbocensus",
        "id": 522
      }
    },
    {
      "lat": -33.43777317341627,
      "lng": -70.54317483124203,
      "meta": {
        "source": "arbocensus",
        "id": 517
      }
    },
    {
      "lat": -33.43748070059301,
      "lng": -70.54166479066659,
      "meta": {
        "source": "arbocensus",
        "id": 518
      }
    },
    {
      "lat": -33.43646573090676,
      "lng": -70.54388155235856,
      "meta": {
        "source": "arbocensus",
        "id": 519
      }
    },
    {
      "lat": -33.43545555987335,
      "lng": -70.5442455286926,
      "meta": {
        "source": "arbocensus",
        "id": 523
      }
    },
    {
      "lat": -33.43446492285363,
      "lng": -70.5459936146765,
      "meta": {
        "source": "arbocensus",
        "id": 532
      }
    },
    {
      "lat": -33.434909100944324,
      "lng": -70.54423000899529,
      "meta": {
        "source": "arbocensus",
        "id": 524
      }
    },
    {
      "lat": -33.434750377190554,
      "lng": -70.54573407036682,
      "meta": {
        "source": "arbocensus",
        "id": 529
      }
    },
    {
      "lat": -33.43482583486513,
      "lng": -70.54408768184263,
      "meta": {
        "source": "arbocensus",
        "id": 525
      }
    },
    {
      "lat": -33.434359864595926,
      "lng": -70.54516468132792,
      "meta": {
        "source": "arbocensus",
        "id": 526
      }
    },
    {
      "lat": -33.43496189563998,
      "lng": -70.54568251819462,
      "meta": {
        "source": "arbocensus",
        "id": 530
      }
    },
    {
      "lat": -33.43493906752145,
      "lng": -70.54568995548381,
      "meta": {
        "source": "arbocensus",
        "id": 531
      }
    },
    {
      "lat": -33.43553949174013,
      "lng": -70.54592086230987,
      "meta": {
        "source": "arbocensus",
        "id": 535
      }
    },
    {
      "lat": -33.43436830920436,
      "lng": -70.54533751120584,
      "meta": {
        "source": "arbocensus",
        "id": 537
      }
    },
    {
      "lat": -33.43432853933728,
      "lng": -70.54506510214654,
      "meta": {
        "source": "arbocensus",
        "id": 538
      }
    },
    {
      "lat": -33.434241485848915,
      "lng": -70.54417565517912,
      "meta": {
        "source": "arbocensus",
        "id": 539
      }
    },
    {
      "lat": -33.43537877123453,
      "lng": -70.54341460682258,
      "meta": {
        "source": "arbocensus",
        "id": 541
      }
    },
    {
      "lat": -33.4349448912848,
      "lng": -70.54151550154344,
      "meta": {
        "source": "arbocensus",
        "id": 543
      }
    },
    {
      "lat": -33.43499598685135,
      "lng": -70.54108483363817,
      "meta": {
        "source": "arbocensus",
        "id": 544
      }
    },
    {
      "lat": -33.43509534045094,
      "lng": -70.54037787326932,
      "meta": {
        "source": "arbocensus",
        "id": 545
      }
    },
    {
      "lat": -33.435182572047566,
      "lng": -70.54005204520499,
      "meta": {
        "source": "arbocensus",
        "id": 546
      }
    },
    {
      "lat": -33.435454986914024,
      "lng": -70.53894717967873,
      "meta": {
        "source": "arbocensus",
        "id": 547
      }
    },
    {
      "lat": -33.43536311207148,
      "lng": -70.53962922844273,
      "meta": {
        "source": "arbocensus",
        "id": 548
      }
    },
    {
      "lat": -33.435287663095274,
      "lng": -70.54010907097808,
      "meta": {
        "source": "arbocensus",
        "id": 549
      }
    },
    {
      "lat": -33.4352059,
      "lng": -70.540504,
      "meta": {
        "source": "arbocensus",
        "id": 550
      }
    },
    {
      "lat": -33.434993679551454,
      "lng": -70.54193320790604,
      "meta": {
        "source": "arbocensus",
        "id": 551
      }
    },
    {
      "lat": -33.43388174559529,
      "lng": -70.54290326128769,
      "meta": {
        "source": "arbocensus",
        "id": 552
      }
    },
    {
      "lat": -33.43447364519697,
      "lng": -70.54431533375931,
      "meta": {
        "source": "arbocensus",
        "id": 554
      }
    },
    {
      "lat": -33.43408754065275,
      "lng": -70.5443914560769,
      "meta": {
        "source": "arbocensus",
        "id": 555
      }
    },
    {
      "lat": -33.434086457759065,
      "lng": -70.54429318159687,
      "meta": {
        "source": "arbocensus",
        "id": 556
      }
    },
    {
      "lat": -33.43414196092591,
      "lng": -70.5448593566033,
      "meta": {
        "source": "arbocensus",
        "id": 557
      }
    },
    {
      "lat": -33.43420925313487,
      "lng": -70.54518477517068,
      "meta": {
        "source": "arbocensus",
        "id": 560
      }
    },
    {
      "lat": -33.434229347123704,
      "lng": -70.54541306989775,
      "meta": {
        "source": "arbocensus",
        "id": 561
      }
    },
    {
      "lat": -33.4372954399158,
      "lng": -70.54881903736506,
      "meta": {
        "source": "arbocensus",
        "id": 562
      }
    },
    {
      "lat": -33.43587696930239,
      "lng": -70.54852397324548,
      "meta": {
        "source": "arbocensus",
        "id": 563
      }
    },
    {
      "lat": -33.43624479274766,
      "lng": -70.54816755958183,
      "meta": {
        "source": "arbocensus",
        "id": 564
      }
    },
    {
      "lat": -33.43660095484314,
      "lng": -70.54818049128002,
      "meta": {
        "source": "arbocensus",
        "id": 565
      }
    },
    {
      "lat": -33.4367689,
      "lng": -70.5481272,
      "meta": {
        "source": "arbocensus",
        "id": 566
      }
    },
    {
      "lat": -33.43444909906895,
      "lng": -70.54748165918399,
      "meta": {
        "source": "arbocensus",
        "id": 689
      }
    },
    {
      "lat": -33.43672019499497,
      "lng": -70.54316236795941,
      "meta": {
        "source": "arbocensus",
        "id": 663
      }
    },
    {
      "lat": -33.43667549839173,
      "lng": -70.54339963944105,
      "meta": {
        "source": "arbocensus",
        "id": 664
      }
    },
    {
      "lat": -33.43666419330471,
      "lng": -70.5434921090953,
      "meta": {
        "source": "arbocensus",
        "id": 665
      }
    },
    {
      "lat": -33.43660955590674,
      "lng": -70.54392864702926,
      "meta": {
        "source": "arbocensus",
        "id": 666
      }
    },
    {
      "lat": -33.436592590942446,
      "lng": -70.54393651115977,
      "meta": {
        "source": "arbocensus",
        "id": 667
      }
    },
    {
      "lat": -33.436553472267,
      "lng": -70.54407761119421,
      "meta": {
        "source": "arbocensus",
        "id": 668
      }
    },
    {
      "lat": -33.43649927583067,
      "lng": -70.5443336492418,
      "meta": {
        "source": "arbocensus",
        "id": 669
      }
    },
    {
      "lat": -33.44067921345106,
      "lng": -70.54330811826473,
      "meta": {
        "source": "arbocensus",
        "id": 1383
      }
    },
    {
      "lat": -33.436498800993114,
      "lng": -70.54444330592156,
      "meta": {
        "source": "arbocensus",
        "id": 670
      }
    },
    {
      "lat": -33.436496699991736,
      "lng": -70.54453854753956,
      "meta": {
        "source": "arbocensus",
        "id": 671
      }
    },
    {
      "lat": -33.4364625448167,
      "lng": -70.5448873396755,
      "meta": {
        "source": "arbocensus",
        "id": 672
      }
    },
    {
      "lat": -33.43645453639472,
      "lng": -70.54487383419128,
      "meta": {
        "source": "arbocensus",
        "id": 673
      }
    },
    {
      "lat": -33.43646259780598,
      "lng": -70.54490006038365,
      "meta": {
        "source": "arbocensus",
        "id": 674
      }
    },
    {
      "lat": -33.434454310656086,
      "lng": -70.54738592263395,
      "meta": {
        "source": "arbocensus",
        "id": 691
      }
    },
    {
      "lat": -33.43639743157042,
      "lng": -70.54528247179887,
      "meta": {
        "source": "arbocensus",
        "id": 675
      }
    },
    {
      "lat": -33.43643123121915,
      "lng": -70.54510992968686,
      "meta": {
        "source": "arbocensus",
        "id": 676
      }
    },
    {
      "lat": -33.4362132469458,
      "lng": -70.54634923529481,
      "meta": {
        "source": "arbocensus",
        "id": 677
      }
    },
    {
      "lat": -33.436494494254035,
      "lng": -70.54639641489736,
      "meta": {
        "source": "arbocensus",
        "id": 678
      }
    },
    {
      "lat": -33.43652927988955,
      "lng": -70.54641011179889,
      "meta": {
        "source": "arbocensus",
        "id": 679
      }
    },
    {
      "lat": -33.43640462421713,
      "lng": -70.54638018591908,
      "meta": {
        "source": "arbocensus",
        "id": 680
      }
    },
    {
      "lat": -33.43594500307768,
      "lng": -70.54694087040764,
      "meta": {
        "source": "arbocensus",
        "id": 681
      }
    },
    {
      "lat": -33.434850917198354,
      "lng": -70.55064321120373,
      "meta": {
        "source": "arbocensus",
        "id": 682
      }
    },
    {
      "lat": -33.4345383,
      "lng": -70.54788,
      "meta": {
        "source": "arbocensus",
        "id": 683
      }
    },
    {
      "lat": -33.43448995525112,
      "lng": -70.54770061120736,
      "meta": {
        "source": "arbocensus",
        "id": 685
      }
    },
    {
      "lat": -33.43449808715701,
      "lng": -70.54764373271563,
      "meta": {
        "source": "arbocensus",
        "id": 686
      }
    },
    {
      "lat": -33.44073953788946,
      "lng": -70.54331433714684,
      "meta": {
        "source": "arbocensus",
        "id": 1381
      }
    },
    {
      "lat": -33.43460886983707,
      "lng": -70.54719498819804,
      "meta": {
        "source": "arbocensus",
        "id": 746
      }
    },
    {
      "lat": -33.441536349515836,
      "lng": -70.54337764065144,
      "meta": {
        "source": "arbocensus",
        "id": 1384
      }
    },
    {
      "lat": -33.44204467592857,
      "lng": -70.54395776907863,
      "meta": {
        "source": "arbocensus",
        "id": 1397
      }
    },
    {
      "lat": -33.44222930935258,
      "lng": -70.54340838382014,
      "meta": {
        "source": "arbocensus",
        "id": 1399
      }
    },
    {
      "lat": -33.44199228560468,
      "lng": -70.54417001617306,
      "meta": {
        "source": "arbocensus",
        "id": 1398
      }
    },
    {
      "lat": -33.44220259445642,
      "lng": -70.5434000567713,
      "meta": {
        "source": "arbocensus",
        "id": 1400
      }
    },
    {
      "lat": -33.4422674501604,
      "lng": -70.54341678421653,
      "meta": {
        "source": "arbocensus",
        "id": 1414
      }
    },
    {
      "lat": -33.44204558851621,
      "lng": -70.54322616181386,
      "meta": {
        "source": "arbocensus",
        "id": 1415
      }
    },
    {
      "lat": -33.44222297918928,
      "lng": -70.54324344181515,
      "meta": {
        "source": "arbocensus",
        "id": 1416
      }
    },
    {
      "lat": -33.44250770619368,
      "lng": -70.54230382471623,
      "meta": {
        "source": "arbocensus",
        "id": 1435
      }
    },
    {
      "lat": -33.4348519112264,
      "lng": -70.54901205791018,
      "meta": {
        "source": "arbocensus",
        "id": 741
      }
    },
    {
      "lat": -33.43450320164228,
      "lng": -70.54647520806391,
      "meta": {
        "source": "arbocensus",
        "id": 750
      }
    },
    {
      "lat": -33.434632558001006,
      "lng": -70.5474963051769,
      "meta": {
        "source": "arbocensus",
        "id": 743
      }
    },
    {
      "lat": -33.434547326251575,
      "lng": -70.5467501345663,
      "meta": {
        "source": "arbocensus",
        "id": 747
      }
    },
    {
      "lat": -33.43462535117392,
      "lng": -70.54738432130576,
      "meta": {
        "source": "arbocensus",
        "id": 744
      }
    },
    {
      "lat": -33.43463033709466,
      "lng": -70.5474404493043,
      "meta": {
        "source": "arbocensus",
        "id": 745
      }
    },
    {
      "lat": -33.43454064142702,
      "lng": -70.54671272455984,
      "meta": {
        "source": "arbocensus",
        "id": 748
      }
    },
    {
      "lat": -33.43450338894249,
      "lng": -70.54647865064453,
      "meta": {
        "source": "arbocensus",
        "id": 749
      }
    },
    {
      "lat": -33.43415988206394,
      "lng": -70.54352190681807,
      "meta": {
        "source": "arbocensus",
        "id": 752
      }
    },
    {
      "lat": -33.436778976868645,
      "lng": -70.54270210173213,
      "meta": {
        "source": "arbocensus",
        "id": 766
      }
    },
    {
      "lat": -33.436792300790046,
      "lng": -70.54265606509065,
      "meta": {
        "source": "arbocensus",
        "id": 768
      }
    },
    {
      "lat": -33.43419931375061,
      "lng": -70.54386515623199,
      "meta": {
        "source": "arbocensus",
        "id": 751
      }
    },
    {
      "lat": -33.44023468719349,
      "lng": -70.55231651689859,
      "meta": {
        "source": "arbocensus",
        "id": 835
      }
    },
    {
      "lat": -33.434648616429094,
      "lng": -70.54760113018824,
      "meta": {
        "source": "arbocensus",
        "id": 742
      }
    },
    {
      "lat": -33.436812510846075,
      "lng": -70.54260771742729,
      "meta": {
        "source": "arbocensus",
        "id": 772
      }
    },
    {
      "lat": -33.43953224365209,
      "lng": -70.5522195725364,
      "meta": {
        "source": "arbocensus",
        "id": 824
      }
    },
    {
      "lat": -33.43681257333164,
      "lng": -70.54260242455986,
      "meta": {
        "source": "arbocensus",
        "id": 774
      }
    },
    {
      "lat": -33.4367968,
      "lng": -70.5426617,
      "meta": {
        "source": "arbocensus",
        "id": 769
      }
    },
    {
      "lat": -33.43682431434824,
      "lng": -70.54248411855869,
      "meta": {
        "source": "arbocensus",
        "id": 776
      }
    },
    {
      "lat": -33.436825098966374,
      "lng": -70.54248925353177,
      "meta": {
        "source": "arbocensus",
        "id": 777
      }
    },
    {
      "lat": -33.43481083818029,
      "lng": -70.54259890657687,
      "meta": {
        "source": "arbocensus",
        "id": 805
      }
    },
    {
      "lat": -33.43681963996597,
      "lng": -70.54243000298283,
      "meta": {
        "source": "arbocensus",
        "id": 778
      }
    },
    {
      "lat": -33.43692205915294,
      "lng": -70.54192226921181,
      "meta": {
        "source": "arbocensus",
        "id": 780
      }
    },
    {
      "lat": -33.43686675119665,
      "lng": -70.54236392289177,
      "meta": {
        "source": "arbocensus",
        "id": 781
      }
    },
    {
      "lat": -33.44039325949766,
      "lng": -70.55246571610584,
      "meta": {
        "source": "arbocensus",
        "id": 851
      }
    },
    {
      "lat": -33.434976035385944,
      "lng": -70.54192200146161,
      "meta": {
        "source": "arbocensus",
        "id": 808
      }
    },
    {
      "lat": -33.43686751941742,
      "lng": -70.5423182872203,
      "meta": {
        "source": "arbocensus",
        "id": 783
      }
    },
    {
      "lat": -33.43686772702977,
      "lng": -70.54226706892423,
      "meta": {
        "source": "arbocensus",
        "id": 785
      }
    },
    {
      "lat": -33.43507381900628,
      "lng": -70.54151798924765,
      "meta": {
        "source": "arbocensus",
        "id": 809
      }
    },
    {
      "lat": -33.43967025118188,
      "lng": -70.55227368329898,
      "meta": {
        "source": "arbocensus",
        "id": 826
      }
    },
    {
      "lat": -33.436700361051656,
      "lng": -70.54274477069244,
      "meta": {
        "source": "arbocensus",
        "id": 790
      }
    },
    {
      "lat": -33.43507543183543,
      "lng": -70.54140939303016,
      "meta": {
        "source": "arbocensus",
        "id": 810
      }
    },
    {
      "lat": -33.436714161898905,
      "lng": -70.542660834926,
      "meta": {
        "source": "arbocensus",
        "id": 793
      }
    },
    {
      "lat": -33.43534973844968,
      "lng": -70.54044895164726,
      "meta": {
        "source": "arbocensus",
        "id": 811
      }
    },
    {
      "lat": -33.43671177618174,
      "lng": -70.54255581684035,
      "meta": {
        "source": "arbocensus",
        "id": 795
      }
    },
    {
      "lat": -33.44018139575658,
      "lng": -70.55249876505688,
      "meta": {
        "source": "arbocensus",
        "id": 837
      }
    },
    {
      "lat": -33.43672119425418,
      "lng": -70.54250880336636,
      "meta": {
        "source": "arbocensus",
        "id": 797
      }
    },
    {
      "lat": -33.4354605624903,
      "lng": -70.54046063359094,
      "meta": {
        "source": "arbocensus",
        "id": 812
      }
    },
    {
      "lat": -33.43681088615975,
      "lng": -70.54202219314789,
      "meta": {
        "source": "arbocensus",
        "id": 799
      }
    },
    {
      "lat": -33.43561124202226,
      "lng": -70.54049299302655,
      "meta": {
        "source": "arbocensus",
        "id": 813
      }
    },
    {
      "lat": -33.43688569044644,
      "lng": -70.5416160149512,
      "meta": {
        "source": "arbocensus",
        "id": 801
      }
    },
    {
      "lat": -33.43963146854516,
      "lng": -70.5522752002065,
      "meta": {
        "source": "arbocensus",
        "id": 825
      }
    },
    {
      "lat": -33.43560648798698,
      "lng": -70.54050550896879,
      "meta": {
        "source": "arbocensus",
        "id": 814
      }
    },
    {
      "lat": -33.43583902869538,
      "lng": -70.54046356801062,
      "meta": {
        "source": "arbocensus",
        "id": 815
      }
    },
    {
      "lat": -33.440376470207,
      "lng": -70.55259626110714,
      "meta": {
        "source": "arbocensus",
        "id": 843
      }
    },
    {
      "lat": -33.43614220907929,
      "lng": -70.54055648959253,
      "meta": {
        "source": "arbocensus",
        "id": 816
      }
    },
    {
      "lat": -33.43972192607213,
      "lng": -70.55227928516878,
      "meta": {
        "source": "arbocensus",
        "id": 828
      }
    },
    {
      "lat": -33.43642454982142,
      "lng": -70.54060983222134,
      "meta": {
        "source": "arbocensus",
        "id": 817
      }
    },
    {
      "lat": -33.43703035645515,
      "lng": -70.54065569888616,
      "meta": {
        "source": "arbocensus",
        "id": 818
      }
    },
    {
      "lat": -33.44034483655516,
      "lng": -70.55256535577712,
      "meta": {
        "source": "arbocensus",
        "id": 839
      }
    },
    {
      "lat": -33.4370229,
      "lng": -70.5406288,
      "meta": {
        "source": "arbocensus",
        "id": 819
      }
    },
    {
      "lat": -33.440025073880555,
      "lng": -70.54303249639553,
      "meta": {
        "source": "arbocensus",
        "id": 827
      }
    },
    {
      "lat": -33.437028682958044,
      "lng": -70.54060216052974,
      "meta": {
        "source": "arbocensus",
        "id": 820
      }
    },
    {
      "lat": -33.437026454941225,
      "lng": -70.54047861820472,
      "meta": {
        "source": "arbocensus",
        "id": 821
      }
    },
    {
      "lat": -33.435906261952844,
      "lng": -70.54280057198828,
      "meta": {
        "source": "arbocensus",
        "id": 836
      }
    },
    {
      "lat": -33.43705039041621,
      "lng": -70.54033637568651,
      "meta": {
        "source": "arbocensus",
        "id": 822
      }
    },
    {
      "lat": -33.439498892755196,
      "lng": -70.55195859827862,
      "meta": {
        "source": "arbocensus",
        "id": 829
      }
    },
    {
      "lat": -33.436954531927924,
      "lng": -70.5429048209574,
      "meta": {
        "source": "arbocensus",
        "id": 823
      }
    },
    {
      "lat": -33.43991142886205,
      "lng": -70.55235262445878,
      "meta": {
        "source": "arbocensus",
        "id": 830
      }
    },
    {
      "lat": -33.44019282155566,
      "lng": -70.55249836979138,
      "meta": {
        "source": "arbocensus",
        "id": 838
      }
    },
    {
      "lat": -33.439956627313954,
      "lng": -70.55238588620043,
      "meta": {
        "source": "arbocensus",
        "id": 833
      }
    },
    {
      "lat": -33.43955521460664,
      "lng": -70.55219240925057,
      "meta": {
        "source": "arbocensus",
        "id": 832
      }
    },
    {
      "lat": -33.43562532445316,
      "lng": -70.54280461598802,
      "meta": {
        "source": "arbocensus",
        "id": 831
      }
    },
    {
      "lat": -33.44010139445684,
      "lng": -70.55242269260069,
      "meta": {
        "source": "arbocensus",
        "id": 834
      }
    },
    {
      "lat": -33.44031489458981,
      "lng": -70.55238384884784,
      "meta": {
        "source": "arbocensus",
        "id": 844
      }
    },
    {
      "lat": -33.4406414100635,
      "lng": -70.5526991958805,
      "meta": {
        "source": "arbocensus",
        "id": 848
      }
    },
    {
      "lat": -33.440445760595104,
      "lng": -70.55263446707158,
      "meta": {
        "source": "arbocensus",
        "id": 846
      }
    },
    {
      "lat": -33.44038059066187,
      "lng": -70.55259197888402,
      "meta": {
        "source": "arbocensus",
        "id": 842
      }
    },
    {
      "lat": -33.440024003780856,
      "lng": -70.55229047568764,
      "meta": {
        "source": "arbocensus",
        "id": 841
      }
    },
    {
      "lat": -33.43581547784125,
      "lng": -70.54280003121146,
      "meta": {
        "source": "arbocensus",
        "id": 840
      }
    },
    {
      "lat": -33.44145863269007,
      "lng": -70.55282782944354,
      "meta": {
        "source": "arbocensus",
        "id": 854
      }
    },
    {
      "lat": -33.44031041405469,
      "lng": -70.55252284477936,
      "meta": {
        "source": "arbocensus",
        "id": 847
      }
    },
    {
      "lat": -33.435784804968286,
      "lng": -70.54281999065684,
      "meta": {
        "source": "arbocensus",
        "id": 845
      }
    },
    {
      "lat": -33.440169127659004,
      "lng": -70.55248128407332,
      "meta": {
        "source": "arbocensus",
        "id": 850
      }
    },
    {
      "lat": -33.43511225208157,
      "lng": -70.54274107057002,
      "meta": {
        "source": "arbocensus",
        "id": 849
      }
    },
    {
      "lat": -33.4411982371073,
      "lng": -70.55281681121828,
      "meta": {
        "source": "arbocensus",
        "id": 855
      }
    },
    {
      "lat": -33.44142037148888,
      "lng": -70.55278333102129,
      "meta": {
        "source": "arbocensus",
        "id": 853
      }
    },
    {
      "lat": -33.434770334113765,
      "lng": -70.54275290552475,
      "meta": {
        "source": "arbocensus",
        "id": 852
      }
    },
    {
      "lat": -33.44091869589834,
      "lng": -70.55267387854767,
      "meta": {
        "source": "arbocensus",
        "id": 861
      }
    },
    {
      "lat": -33.44133437945863,
      "lng": -70.55282542232305,
      "meta": {
        "source": "arbocensus",
        "id": 856
      }
    },
    {
      "lat": -33.44127158509847,
      "lng": -70.55288042552205,
      "meta": {
        "source": "arbocensus",
        "id": 857
      }
    },
    {
      "lat": -33.44127847820929,
      "lng": -70.55277203869937,
      "meta": {
        "source": "arbocensus",
        "id": 860
      }
    },
    {
      "lat": -33.44135342351665,
      "lng": -70.55279214272711,
      "meta": {
        "source": "arbocensus",
        "id": 862
      }
    },
    {
      "lat": -33.43516831333992,
      "lng": -70.54276291578618,
      "meta": {
        "source": "arbocensus",
        "id": 859
      }
    },
    {
      "lat": -33.440697635444565,
      "lng": -70.55257651416721,
      "meta": {
        "source": "arbocensus",
        "id": 863
      }
    },
    {
      "lat": -33.43492451753733,
      "lng": -70.54277416833652,
      "meta": {
        "source": "arbocensus",
        "id": 866
      }
    },
    {
      "lat": -33.43498949349285,
      "lng": -70.54274585817906,
      "meta": {
        "source": "arbocensus",
        "id": 864
      }
    },
    {
      "lat": -33.44080693221656,
      "lng": -70.55258164701138,
      "meta": {
        "source": "arbocensus",
        "id": 865
      }
    },
    {
      "lat": -33.439870541804446,
      "lng": -70.55217379675241,
      "meta": {
        "source": "arbocensus",
        "id": 867
      }
    },
    {
      "lat": -33.43988881652043,
      "lng": -70.55223160432597,
      "meta": {
        "source": "arbocensus",
        "id": 873
      }
    },
    {
      "lat": -33.43438032429791,
      "lng": -70.54265986829411,
      "meta": {
        "source": "arbocensus",
        "id": 877
      }
    },
    {
      "lat": -33.44173554229959,
      "lng": -70.54337486593604,
      "meta": {
        "source": "arbocensus",
        "id": 1387
      }
    },
    {
      "lat": -33.442156721284086,
      "lng": -70.54341137184466,
      "meta": {
        "source": "arbocensus",
        "id": 1401
      }
    },
    {
      "lat": -33.44234803588965,
      "lng": -70.54347416350153,
      "meta": {
        "source": "arbocensus",
        "id": 1402
      }
    },
    {
      "lat": -33.442403548005444,
      "lng": -70.54326704321095,
      "meta": {
        "source": "arbocensus",
        "id": 1419
      }
    },
    {
      "lat": -33.44230055023838,
      "lng": -70.54338253375971,
      "meta": {
        "source": "arbocensus",
        "id": 1420
      }
    },
    {
      "lat": -33.44231849407901,
      "lng": -70.54326229684317,
      "meta": {
        "source": "arbocensus",
        "id": 1423
      }
    },
    {
      "lat": -33.442229953209946,
      "lng": -70.5432120426448,
      "meta": {
        "source": "arbocensus",
        "id": 1422
      }
    },
    {
      "lat": -33.44227087453727,
      "lng": -70.5431988833741,
      "meta": {
        "source": "arbocensus",
        "id": 1424
      }
    },
    {
      "lat": -33.442031347133934,
      "lng": -70.54333431187959,
      "meta": {
        "source": "arbocensus",
        "id": 1426
      }
    },
    {
      "lat": -33.442387236830015,
      "lng": -70.54325140076755,
      "meta": {
        "source": "arbocensus",
        "id": 1427
      }
    },
    {
      "lat": -33.44242086837873,
      "lng": -70.54252173813104,
      "meta": {
        "source": "arbocensus",
        "id": 1436
      }
    },
    {
      "lat": -33.442969009574114,
      "lng": -70.54327453863479,
      "meta": {
        "source": "arbocensus",
        "id": 1438
      }
    },
    {
      "lat": -33.4428878137891,
      "lng": -70.54344179963873,
      "meta": {
        "source": "arbocensus",
        "id": 1451
      }
    },
    {
      "lat": -33.44332301664829,
      "lng": -70.54331947825752,
      "meta": {
        "source": "arbocensus",
        "id": 1453
      }
    },
    {
      "lat": -33.443515733922766,
      "lng": -70.54333036551321,
      "meta": {
        "source": "arbocensus",
        "id": 1457
      }
    },
    {
      "lat": -33.44401167031161,
      "lng": -70.54351604910026,
      "meta": {
        "source": "arbocensus",
        "id": 1462
      }
    },
    {
      "lat": -33.44291024407685,
      "lng": -70.54334868977621,
      "meta": {
        "source": "arbocensus",
        "id": 1463
      }
    },
    {
      "lat": -33.43676680594845,
      "lng": -70.54657476137947,
      "meta": {
        "source": "arbocensus",
        "id": 1624
      }
    },
    {
      "lat": -33.43677540905891,
      "lng": -70.54301566577978,
      "meta": {
        "source": "arbocensus",
        "id": 1575
      }
    },
    {
      "lat": -33.4362344490316,
      "lng": -70.54816276779343,
      "meta": {
        "source": "arbocensus",
        "id": 1592
      }
    },
    {
      "lat": -33.43668604254579,
      "lng": -70.54656072322986,
      "meta": {
        "source": "arbocensus",
        "id": 1617
      }
    },
    {
      "lat": -33.43668479090818,
      "lng": -70.54657217926746,
      "meta": {
        "source": "arbocensus",
        "id": 1620
      }
    },
    {
      "lat": -33.434663026536676,
      "lng": -70.54818756151194,
      "meta": {
        "source": "arbocensus",
        "id": 1683
      }
    },
    {
      "lat": -33.43440564478948,
      "lng": -70.54696366461307,
      "meta": {
        "source": "arbocensus",
        "id": 1699
      }
    },
    {
      "lat": -33.4344090156137,
      "lng": -70.54698265748056,
      "meta": {
        "source": "arbocensus",
        "id": 1701
      }
    },
    {
      "lat": -33.43437372391054,
      "lng": -70.5453008627715,
      "meta": {
        "source": "arbocensus",
        "id": 1704
      }
    },
    {
      "lat": -33.43999475951501,
      "lng": -70.55225961545386,
      "meta": {
        "source": "arbocensus",
        "id": 871
      }
    },
    {
      "lat": -33.43427516654134,
      "lng": -70.54284464163428,
      "meta": {
        "source": "arbocensus",
        "id": 930
      }
    },
    {
      "lat": -33.43999510236441,
      "lng": -70.55223996937079,
      "meta": {
        "source": "arbocensus",
        "id": 872
      }
    },
    {
      "lat": -33.43450270820834,
      "lng": -70.5427198019525,
      "meta": {
        "source": "arbocensus",
        "id": 870
      }
    },
    {
      "lat": -33.43782130769007,
      "lng": -70.55147114208319,
      "meta": {
        "source": "arbocensus",
        "id": 910
      }
    },
    {
      "lat": -33.4344682888005,
      "lng": -70.54265632207154,
      "meta": {
        "source": "arbocensus",
        "id": 875
      }
    },
    {
      "lat": -33.438213961711796,
      "lng": -70.55154857790801,
      "meta": {
        "source": "arbocensus",
        "id": 909
      }
    },
    {
      "lat": -33.439784033377066,
      "lng": -70.55212186962176,
      "meta": {
        "source": "arbocensus",
        "id": 874
      }
    },
    {
      "lat": -33.43972837132668,
      "lng": -70.552196045586,
      "meta": {
        "source": "arbocensus",
        "id": 876
      }
    },
    {
      "lat": -33.4337781274408,
      "lng": -70.54175641181935,
      "meta": {
        "source": "arbocensus",
        "id": 906
      }
    },
    {
      "lat": -33.439630487691296,
      "lng": -70.55210519236309,
      "meta": {
        "source": "arbocensus",
        "id": 878
      }
    },
    {
      "lat": -33.439217622909275,
      "lng": -70.55199610338082,
      "meta": {
        "source": "arbocensus",
        "id": 881
      }
    },
    {
      "lat": -33.43970112952646,
      "lng": -70.5506254127611,
      "meta": {
        "source": "arbocensus",
        "id": 950
      }
    },
    {
      "lat": -33.43955634288685,
      "lng": -70.55222783300363,
      "meta": {
        "source": "arbocensus",
        "id": 880
      }
    },
    {
      "lat": -33.43903146378663,
      "lng": -70.5518782390672,
      "meta": {
        "source": "arbocensus",
        "id": 883
      }
    },
    {
      "lat": -33.43490221932144,
      "lng": -70.54422973999682,
      "meta": {
        "source": "arbocensus",
        "id": 931
      }
    },
    {
      "lat": -33.43898478286439,
      "lng": -70.55197036420974,
      "meta": {
        "source": "arbocensus",
        "id": 884
      }
    },
    {
      "lat": -33.43870713213733,
      "lng": -70.55194723641176,
      "meta": {
        "source": "arbocensus",
        "id": 911
      }
    },
    {
      "lat": -33.4388113480249,
      "lng": -70.55180440177195,
      "meta": {
        "source": "arbocensus",
        "id": 885
      }
    },
    {
      "lat": -33.43402054958399,
      "lng": -70.54267752143909,
      "meta": {
        "source": "arbocensus",
        "id": 882
      }
    },
    {
      "lat": -33.43834282519387,
      "lng": -70.55163351269779,
      "meta": {
        "source": "arbocensus",
        "id": 912
      }
    },
    {
      "lat": -33.43896411073242,
      "lng": -70.55187670415185,
      "meta": {
        "source": "arbocensus",
        "id": 886
      }
    },
    {
      "lat": -33.4387081604372,
      "lng": -70.55190847031265,
      "meta": {
        "source": "arbocensus",
        "id": 887
      }
    },
    {
      "lat": -33.438774600929584,
      "lng": -70.55181527250261,
      "meta": {
        "source": "arbocensus",
        "id": 888
      }
    },
    {
      "lat": -33.43831254226068,
      "lng": -70.55156787918294,
      "meta": {
        "source": "arbocensus",
        "id": 914
      }
    },
    {
      "lat": -33.43884759297572,
      "lng": -70.5520039746551,
      "meta": {
        "source": "arbocensus",
        "id": 889
      }
    },
    {
      "lat": -33.43849903447731,
      "lng": -70.5517425131859,
      "meta": {
        "source": "arbocensus",
        "id": 890
      }
    },
    {
      "lat": -33.43968259872915,
      "lng": -70.55054494260152,
      "meta": {
        "source": "arbocensus",
        "id": 944
      }
    },
    {
      "lat": -33.43847351151195,
      "lng": -70.55158872747995,
      "meta": {
        "source": "arbocensus",
        "id": 891
      }
    },
    {
      "lat": -33.43376838520524,
      "lng": -70.54160685864723,
      "meta": {
        "source": "arbocensus",
        "id": 913
      }
    },
    {
      "lat": -33.438601004692984,
      "lng": -70.5517290467895,
      "meta": {
        "source": "arbocensus",
        "id": 894
      }
    },
    {
      "lat": -33.438551822654766,
      "lng": -70.55165919885285,
      "meta": {
        "source": "arbocensus",
        "id": 895
      }
    },
    {
      "lat": -33.4348789,
      "lng": -70.5429724,
      "meta": {
        "source": "arbocensus",
        "id": 932
      }
    },
    {
      "lat": -33.4386277288214,
      "lng": -70.55171386530048,
      "meta": {
        "source": "arbocensus",
        "id": 896
      }
    },
    {
      "lat": -33.43847311789246,
      "lng": -70.55181053711537,
      "meta": {
        "source": "arbocensus",
        "id": 897
      }
    },
    {
      "lat": -33.438180861694576,
      "lng": -70.55151825444942,
      "meta": {
        "source": "arbocensus",
        "id": 915
      }
    },
    {
      "lat": -33.43840454723301,
      "lng": -70.5515957186577,
      "meta": {
        "source": "arbocensus",
        "id": 898
      }
    },
    {
      "lat": -33.43847938321226,
      "lng": -70.55176521269406,
      "meta": {
        "source": "arbocensus",
        "id": 899
      }
    },
    {
      "lat": -33.43378969606214,
      "lng": -70.5414794864,
      "meta": {
        "source": "arbocensus",
        "id": 916
      }
    },
    {
      "lat": -33.438513721397136,
      "lng": -70.55170280661582,
      "meta": {
        "source": "arbocensus",
        "id": 900
      }
    },
    {
      "lat": -33.438301699351285,
      "lng": -70.5515308402239,
      "meta": {
        "source": "arbocensus",
        "id": 917
      }
    },
    {
      "lat": -33.43810344850902,
      "lng": -70.55161216950903,
      "meta": {
        "source": "arbocensus",
        "id": 901
      }
    },
    {
      "lat": -33.43822647800775,
      "lng": -70.55146992184747,
      "meta": {
        "source": "arbocensus",
        "id": 903
      }
    },
    {
      "lat": -33.43798820889165,
      "lng": -70.55160503123865,
      "meta": {
        "source": "arbocensus",
        "id": 904
      }
    },
    {
      "lat": -33.433816001267395,
      "lng": -70.54191970950265,
      "meta": {
        "source": "arbocensus",
        "id": 902
      }
    },
    {
      "lat": -33.436354256694266,
      "lng": -70.5429659386592,
      "meta": {
        "source": "arbocensus",
        "id": 933
      }
    },
    {
      "lat": -33.4383694530969,
      "lng": -70.5515133320975,
      "meta": {
        "source": "arbocensus",
        "id": 905
      }
    },
    {
      "lat": -33.43824518777098,
      "lng": -70.55147019325402,
      "meta": {
        "source": "arbocensus",
        "id": 918
      }
    },
    {
      "lat": -33.438271424912706,
      "lng": -70.55157858075202,
      "meta": {
        "source": "arbocensus",
        "id": 907
      }
    },
    {
      "lat": -33.43785635952306,
      "lng": -70.5515249102102,
      "meta": {
        "source": "arbocensus",
        "id": 908
      }
    },
    {
      "lat": -33.43697231562231,
      "lng": -70.54162047342207,
      "meta": {
        "source": "arbocensus",
        "id": 951
      }
    },
    {
      "lat": -33.43823260169444,
      "lng": -70.55140426632454,
      "meta": {
        "source": "arbocensus",
        "id": 920
      }
    },
    {
      "lat": -33.43641881820305,
      "lng": -70.54296493158907,
      "meta": {
        "source": "arbocensus",
        "id": 934
      }
    },
    {
      "lat": -33.43816616936714,
      "lng": -70.55152759879131,
      "meta": {
        "source": "arbocensus",
        "id": 921
      }
    },
    {
      "lat": -33.43371681815529,
      "lng": -70.54114928229839,
      "meta": {
        "source": "arbocensus",
        "id": 919
      }
    },
    {
      "lat": -33.438735241681684,
      "lng": -70.55161874178046,
      "meta": {
        "source": "arbocensus",
        "id": 922
      }
    },
    {
      "lat": -33.43971069760161,
      "lng": -70.55048435302862,
      "meta": {
        "source": "arbocensus",
        "id": 945
      }
    },
    {
      "lat": -33.43804686691919,
      "lng": -70.55145285524813,
      "meta": {
        "source": "arbocensus",
        "id": 923
      }
    },
    {
      "lat": -33.4392862382443,
      "lng": -70.55224724931827,
      "meta": {
        "source": "arbocensus",
        "id": 924
      }
    },
    {
      "lat": -33.43932552056466,
      "lng": -70.55243076981262,
      "meta": {
        "source": "arbocensus",
        "id": 925
      }
    },
    {
      "lat": -33.43927837101842,
      "lng": -70.55236050392054,
      "meta": {
        "source": "arbocensus",
        "id": 926
      }
    },
    {
      "lat": -33.43373645179075,
      "lng": -70.54124462658335,
      "meta": {
        "source": "arbocensus",
        "id": 927
      }
    },
    {
      "lat": -33.434213245337546,
      "lng": -70.54285628956046,
      "meta": {
        "source": "arbocensus",
        "id": 929
      }
    },
    {
      "lat": -33.439635518540534,
      "lng": -70.55082625075106,
      "meta": {
        "source": "arbocensus",
        "id": 938
      }
    },
    {
      "lat": -33.439656501416216,
      "lng": -70.55102189921857,
      "meta": {
        "source": "arbocensus",
        "id": 939
      }
    },
    {
      "lat": -33.43969654896789,
      "lng": -70.55049547888663,
      "meta": {
        "source": "arbocensus",
        "id": 947
      }
    },
    {
      "lat": -33.43646222959069,
      "lng": -70.54296299236583,
      "meta": {
        "source": "arbocensus",
        "id": 935
      }
    },
    {
      "lat": -33.43960712298411,
      "lng": -70.55123709255902,
      "meta": {
        "source": "arbocensus",
        "id": 940
      }
    },
    {
      "lat": -33.43967754929688,
      "lng": -70.55061178197475,
      "meta": {
        "source": "arbocensus",
        "id": 941
      }
    },
    {
      "lat": -33.4396561129499,
      "lng": -70.55069959611211,
      "meta": {
        "source": "arbocensus",
        "id": 946
      }
    },
    {
      "lat": -33.439651659847506,
      "lng": -70.55061517771804,
      "meta": {
        "source": "arbocensus",
        "id": 942
      }
    },
    {
      "lat": -33.43966854005099,
      "lng": -70.55069320403524,
      "meta": {
        "source": "arbocensus",
        "id": 943
      }
    },
    {
      "lat": -33.43966146167498,
      "lng": -70.55062885860168,
      "meta": {
        "source": "arbocensus",
        "id": 955
      }
    },
    {
      "lat": -33.43964423296294,
      "lng": -70.55065118283761,
      "meta": {
        "source": "arbocensus",
        "id": 952
      }
    },
    {
      "lat": -33.439656695700904,
      "lng": -70.54998057474889,
      "meta": {
        "source": "arbocensus",
        "id": 948
      }
    },
    {
      "lat": -33.43977608961723,
      "lng": -70.54921231757699,
      "meta": {
        "source": "arbocensus",
        "id": 963
      }
    },
    {
      "lat": -33.43968595455011,
      "lng": -70.55064399400796,
      "meta": {
        "source": "arbocensus",
        "id": 949
      }
    },
    {
      "lat": -33.43957500692104,
      "lng": -70.55014441187969,
      "meta": {
        "source": "arbocensus",
        "id": 957
      }
    },
    {
      "lat": -33.43967274170869,
      "lng": -70.54981485923807,
      "meta": {
        "source": "arbocensus",
        "id": 953
      }
    },
    {
      "lat": -33.43972203462571,
      "lng": -70.55007754580598,
      "meta": {
        "source": "arbocensus",
        "id": 959
      }
    },
    {
      "lat": -33.43697650224603,
      "lng": -70.54152668709536,
      "meta": {
        "source": "arbocensus",
        "id": 954
      }
    },
    {
      "lat": -33.439881494186764,
      "lng": -70.54996038911389,
      "meta": {
        "source": "arbocensus",
        "id": 960
      }
    },
    {
      "lat": -33.43955991912793,
      "lng": -70.54994806246329,
      "meta": {
        "source": "arbocensus",
        "id": 961
      }
    },
    {
      "lat": -33.43971495664632,
      "lng": -70.55007757295807,
      "meta": {
        "source": "arbocensus",
        "id": 958
      }
    },
    {
      "lat": -33.439602448762955,
      "lng": -70.5497284348307,
      "meta": {
        "source": "arbocensus",
        "id": 962
      }
    },
    {
      "lat": -33.43699388728847,
      "lng": -70.54144513988908,
      "meta": {
        "source": "arbocensus",
        "id": 956
      }
    },
    {
      "lat": -33.43972163652889,
      "lng": -70.55005878817929,
      "meta": {
        "source": "arbocensus",
        "id": 968
      }
    },
    {
      "lat": -33.43974801054059,
      "lng": -70.54928651603768,
      "meta": {
        "source": "arbocensus",
        "id": 964
      }
    },
    {
      "lat": -33.439664155932945,
      "lng": -70.55001206069996,
      "meta": {
        "source": "arbocensus",
        "id": 965
      }
    },
    {
      "lat": -33.43972027069944,
      "lng": -70.55006197933997,
      "meta": {
        "source": "arbocensus",
        "id": 967
      }
    },
    {
      "lat": -33.43935609693829,
      "lng": -70.54902552889166,
      "meta": {
        "source": "arbocensus",
        "id": 966
      }
    },
    {
      "lat": -33.43970166332248,
      "lng": -70.54890044215358,
      "meta": {
        "source": "arbocensus",
        "id": 969
      }
    },
    {
      "lat": -33.43963640256736,
      "lng": -70.54954688974244,
      "meta": {
        "source": "arbocensus",
        "id": 970
      }
    },
    {
      "lat": -33.43977252817756,
      "lng": -70.54894134820832,
      "meta": {
        "source": "arbocensus",
        "id": 971
      }
    },
    {
      "lat": -33.43986268977984,
      "lng": -70.54902102558793,
      "meta": {
        "source": "arbocensus",
        "id": 973
      }
    },
    {
      "lat": -33.43970745972605,
      "lng": -70.54888836517883,
      "meta": {
        "source": "arbocensus",
        "id": 972
      }
    },
    {
      "lat": -33.43721140518282,
      "lng": -70.5501817534379,
      "meta": {
        "source": "arbocensus",
        "id": 1007
      }
    },
    {
      "lat": -33.439797444493664,
      "lng": -70.5488045546653,
      "meta": {
        "source": "arbocensus",
        "id": 974
      }
    },
    {
      "lat": -33.43972990378098,
      "lng": -70.54897024062079,
      "meta": {
        "source": "arbocensus",
        "id": 975
      }
    },
    {
      "lat": -33.43974701994619,
      "lng": -70.5487111549273,
      "meta": {
        "source": "arbocensus",
        "id": 976
      }
    },
    {
      "lat": -33.437934233983626,
      "lng": -70.55193712045764,
      "meta": {
        "source": "arbocensus",
        "id": 1008
      }
    },
    {
      "lat": -33.43975351845936,
      "lng": -70.54873715151581,
      "meta": {
        "source": "arbocensus",
        "id": 977
      }
    },
    {
      "lat": -33.4372033581855,
      "lng": -70.55009304427404,
      "meta": {
        "source": "arbocensus",
        "id": 1009
      }
    },
    {
      "lat": -33.439735518886046,
      "lng": -70.54865997277231,
      "meta": {
        "source": "arbocensus",
        "id": 978
      }
    },
    {
      "lat": -33.437570113731944,
      "lng": -70.54808079016807,
      "meta": {
        "source": "arbocensus",
        "id": 1029
      }
    },
    {
      "lat": -33.43976920914406,
      "lng": -70.54893188487372,
      "meta": {
        "source": "arbocensus",
        "id": 979
      }
    },
    {
      "lat": -33.43973653413628,
      "lng": -70.54856012165938,
      "meta": {
        "source": "arbocensus",
        "id": 980
      }
    },
    {
      "lat": -33.439778246972274,
      "lng": -70.54888785468562,
      "meta": {
        "source": "arbocensus",
        "id": 981
      }
    },
    {
      "lat": -33.43973839179951,
      "lng": -70.54873977650271,
      "meta": {
        "source": "arbocensus",
        "id": 982
      }
    },
    {
      "lat": -33.4371839385274,
      "lng": -70.55025708161347,
      "meta": {
        "source": "arbocensus",
        "id": 1010
      }
    },
    {
      "lat": -33.43972646440121,
      "lng": -70.54865406871701,
      "meta": {
        "source": "arbocensus",
        "id": 983
      }
    },
    {
      "lat": -33.4399902927925,
      "lng": -70.54827968623448,
      "meta": {
        "source": "arbocensus",
        "id": 984
      }
    },
    {
      "lat": -33.43720235237459,
      "lng": -70.55031661493877,
      "meta": {
        "source": "arbocensus",
        "id": 1011
      }
    },
    {
      "lat": -33.439900886530125,
      "lng": -70.54858601797876,
      "meta": {
        "source": "arbocensus",
        "id": 985
      }
    },
    {
      "lat": -33.43982283240494,
      "lng": -70.54862147058991,
      "meta": {
        "source": "arbocensus",
        "id": 986
      }
    },
    {
      "lat": -33.437612819475326,
      "lng": -70.54777421292195,
      "meta": {
        "source": "arbocensus",
        "id": 1031
      }
    },
    {
      "lat": -33.439990324664834,
      "lng": -70.54839836569082,
      "meta": {
        "source": "arbocensus",
        "id": 987
      }
    },
    {
      "lat": -33.437289988828375,
      "lng": -70.54985505497417,
      "meta": {
        "source": "arbocensus",
        "id": 1012
      }
    },
    {
      "lat": -33.43996095415162,
      "lng": -70.54793169012886,
      "meta": {
        "source": "arbocensus",
        "id": 989
      }
    },
    {
      "lat": -33.43751059975843,
      "lng": -70.54795692044762,
      "meta": {
        "source": "arbocensus",
        "id": 1030
      }
    },
    {
      "lat": -33.43981054518521,
      "lng": -70.54851898225823,
      "meta": {
        "source": "arbocensus",
        "id": 988
      }
    },
    {
      "lat": -33.437295691696434,
      "lng": -70.54979694657364,
      "meta": {
        "source": "arbocensus",
        "id": 1013
      }
    },
    {
      "lat": -33.439952920112745,
      "lng": -70.54820883180821,
      "meta": {
        "source": "arbocensus",
        "id": 990
      }
    },
    {
      "lat": -33.4398413425469,
      "lng": -70.5484949522536,
      "meta": {
        "source": "arbocensus",
        "id": 991
      }
    },
    {
      "lat": -33.43996533056596,
      "lng": -70.54802924897163,
      "meta": {
        "source": "arbocensus",
        "id": 992
      }
    },
    {
      "lat": -33.43730746239874,
      "lng": -70.54963513355703,
      "meta": {
        "source": "arbocensus",
        "id": 1014
      }
    },
    {
      "lat": -33.4399520184833,
      "lng": -70.54821589849047,
      "meta": {
        "source": "arbocensus",
        "id": 994
      }
    },
    {
      "lat": -33.43998656502241,
      "lng": -70.5482372753764,
      "meta": {
        "source": "arbocensus",
        "id": 993
      }
    },
    {
      "lat": -33.43782679870478,
      "lng": -70.54660972133235,
      "meta": {
        "source": "arbocensus",
        "id": 1043
      }
    },
    {
      "lat": -33.439991337494355,
      "lng": -70.54795619543069,
      "meta": {
        "source": "arbocensus",
        "id": 995
      }
    },
    {
      "lat": -33.43985063921023,
      "lng": -70.54820934916187,
      "meta": {
        "source": "arbocensus",
        "id": 996
      }
    },
    {
      "lat": -33.43721618618952,
      "lng": -70.5497971472978,
      "meta": {
        "source": "arbocensus",
        "id": 1015
      }
    },
    {
      "lat": -33.43991802198673,
      "lng": -70.54740912896294,
      "meta": {
        "source": "arbocensus",
        "id": 997
      }
    },
    {
      "lat": -33.43991627682849,
      "lng": -70.54757780188467,
      "meta": {
        "source": "arbocensus",
        "id": 998
      }
    },
    {
      "lat": -33.43733352333162,
      "lng": -70.54949649744142,
      "meta": {
        "source": "arbocensus",
        "id": 1016
      }
    },
    {
      "lat": -33.43999889912255,
      "lng": -70.54748568321214,
      "meta": {
        "source": "arbocensus",
        "id": 999
      }
    },
    {
      "lat": -33.44002890744717,
      "lng": -70.54726564390644,
      "meta": {
        "source": "arbocensus",
        "id": 1000
      }
    },
    {
      "lat": -33.44011073141194,
      "lng": -70.54722643043704,
      "meta": {
        "source": "arbocensus",
        "id": 1001
      }
    },
    {
      "lat": -33.43732530181361,
      "lng": -70.54938376886388,
      "meta": {
        "source": "arbocensus",
        "id": 1017
      }
    },
    {
      "lat": -33.43709988148816,
      "lng": -70.55080416504441,
      "meta": {
        "source": "arbocensus",
        "id": 1002
      }
    },
    {
      "lat": -33.437108960166476,
      "lng": -70.55083648250711,
      "meta": {
        "source": "arbocensus",
        "id": 1003
      }
    },
    {
      "lat": -33.43755926206663,
      "lng": -70.54774784299222,
      "meta": {
        "source": "arbocensus",
        "id": 1032
      }
    },
    {
      "lat": -33.437108047046536,
      "lng": -70.55069049871368,
      "meta": {
        "source": "arbocensus",
        "id": 1004
      }
    },
    {
      "lat": -33.43735473327569,
      "lng": -70.54950102788872,
      "meta": {
        "source": "arbocensus",
        "id": 1018
      }
    },
    {
      "lat": -33.437126581041454,
      "lng": -70.55071125977028,
      "meta": {
        "source": "arbocensus",
        "id": 1005
      }
    },
    {
      "lat": -33.43761361953836,
      "lng": -70.54775914574914,
      "meta": {
        "source": "arbocensus",
        "id": 1033
      }
    },
    {
      "lat": -33.43712787648593,
      "lng": -70.5508258111646,
      "meta": {
        "source": "arbocensus",
        "id": 1006
      }
    },
    {
      "lat": -33.437351418246585,
      "lng": -70.54954138411178,
      "meta": {
        "source": "arbocensus",
        "id": 1019
      }
    },
    {
      "lat": -33.437366460279236,
      "lng": -70.54932537115704,
      "meta": {
        "source": "arbocensus",
        "id": 1020
      }
    },
    {
      "lat": -33.43737028075458,
      "lng": -70.54921413327428,
      "meta": {
        "source": "arbocensus",
        "id": 1022
      }
    },
    {
      "lat": -33.43768283599275,
      "lng": -70.54754016070277,
      "meta": {
        "source": "arbocensus",
        "id": 1034
      }
    },
    {
      "lat": -33.4372655047612,
      "lng": -70.54943830485392,
      "meta": {
        "source": "arbocensus",
        "id": 1021
      }
    },
    {
      "lat": -33.437697123452125,
      "lng": -70.54757595259791,
      "meta": {
        "source": "arbocensus",
        "id": 1035
      }
    },
    {
      "lat": -33.437347046914475,
      "lng": -70.54937594262714,
      "meta": {
        "source": "arbocensus",
        "id": 1023
      }
    },
    {
      "lat": -33.43733777259987,
      "lng": -70.54924367332535,
      "meta": {
        "source": "arbocensus",
        "id": 1024
      }
    },
    {
      "lat": -33.43749193881458,
      "lng": -70.5488010119855,
      "meta": {
        "source": "arbocensus",
        "id": 1025
      }
    },
    {
      "lat": -33.43789289869661,
      "lng": -70.54622569051921,
      "meta": {
        "source": "arbocensus",
        "id": 1050
      }
    },
    {
      "lat": -33.437502386176526,
      "lng": -70.54845362910397,
      "meta": {
        "source": "arbocensus",
        "id": 1027
      }
    },
    {
      "lat": -33.43728438723493,
      "lng": -70.54876136697185,
      "meta": {
        "source": "arbocensus",
        "id": 1026
      }
    },
    {
      "lat": -33.437568622313016,
      "lng": -70.54794830275821,
      "meta": {
        "source": "arbocensus",
        "id": 1028
      }
    },
    {
      "lat": -33.43778441628363,
      "lng": -70.54657876044352,
      "meta": {
        "source": "arbocensus",
        "id": 1045
      }
    },
    {
      "lat": -33.437681190212494,
      "lng": -70.5473600110957,
      "meta": {
        "source": "arbocensus",
        "id": 1037
      }
    },
    {
      "lat": -33.43823923581396,
      "lng": -70.54590690623128,
      "meta": {
        "source": "arbocensus",
        "id": 1052
      }
    },
    {
      "lat": -33.437598134383215,
      "lng": -70.54767381960642,
      "meta": {
        "source": "arbocensus",
        "id": 1036
      }
    },
    {
      "lat": -33.43783485056701,
      "lng": -70.54629871078252,
      "meta": {
        "source": "arbocensus",
        "id": 1044
      }
    },
    {
      "lat": -33.43773188187595,
      "lng": -70.547100777568,
      "meta": {
        "source": "arbocensus",
        "id": 1038
      }
    },
    {
      "lat": -33.43771784022697,
      "lng": -70.54726844494793,
      "meta": {
        "source": "arbocensus",
        "id": 1039
      }
    },
    {
      "lat": -33.43771094277853,
      "lng": -70.54699279142814,
      "meta": {
        "source": "arbocensus",
        "id": 1040
      }
    },
    {
      "lat": -33.4377478737752,
      "lng": -70.54688089654582,
      "meta": {
        "source": "arbocensus",
        "id": 1041
      }
    },
    {
      "lat": -33.437596601825646,
      "lng": -70.54708945645376,
      "meta": {
        "source": "arbocensus",
        "id": 1042
      }
    },
    {
      "lat": -33.438319456060896,
      "lng": -70.54593438625399,
      "meta": {
        "source": "arbocensus",
        "id": 1061
      }
    },
    {
      "lat": -33.437902550067854,
      "lng": -70.54612404717538,
      "meta": {
        "source": "arbocensus",
        "id": 1046
      }
    },
    {
      "lat": -33.43779208096328,
      "lng": -70.54622460395134,
      "meta": {
        "source": "arbocensus",
        "id": 1048
      }
    },
    {
      "lat": -33.437916153096005,
      "lng": -70.54612818003062,
      "meta": {
        "source": "arbocensus",
        "id": 1049
      }
    },
    {
      "lat": -33.4379911937913,
      "lng": -70.54583959913545,
      "meta": {
        "source": "arbocensus",
        "id": 1056
      }
    },
    {
      "lat": -33.43805919349897,
      "lng": -70.54584696716387,
      "meta": {
        "source": "arbocensus",
        "id": 1051
      }
    },
    {
      "lat": -33.43817863671637,
      "lng": -70.54591271456253,
      "meta": {
        "source": "arbocensus",
        "id": 1053
      }
    },
    {
      "lat": -33.438067630641264,
      "lng": -70.54575757105184,
      "meta": {
        "source": "arbocensus",
        "id": 1054
      }
    },
    {
      "lat": -33.43811168108737,
      "lng": -70.54574697675565,
      "meta": {
        "source": "arbocensus",
        "id": 1060
      }
    },
    {
      "lat": -33.438199433102504,
      "lng": -70.54592439772897,
      "meta": {
        "source": "arbocensus",
        "id": 1055
      }
    },
    {
      "lat": -33.43827350303101,
      "lng": -70.54591054333214,
      "meta": {
        "source": "arbocensus",
        "id": 1057
      }
    },
    {
      "lat": -33.438475481866206,
      "lng": -70.54595484317525,
      "meta": {
        "source": "arbocensus",
        "id": 1062
      }
    },
    {
      "lat": -33.43854517752157,
      "lng": -70.54595408027538,
      "meta": {
        "source": "arbocensus",
        "id": 1064
      }
    },
    {
      "lat": -33.43830202836462,
      "lng": -70.54577181373332,
      "meta": {
        "source": "arbocensus",
        "id": 1063
      }
    },
    {
      "lat": -33.438537105054756,
      "lng": -70.54599340967397,
      "meta": {
        "source": "arbocensus",
        "id": 1066
      }
    },
    {
      "lat": -33.43838238681827,
      "lng": -70.545654113094,
      "meta": {
        "source": "arbocensus",
        "id": 1065
      }
    },
    {
      "lat": -33.43868714091791,
      "lng": -70.54599007076713,
      "meta": {
        "source": "arbocensus",
        "id": 1068
      }
    },
    {
      "lat": -33.43841754270343,
      "lng": -70.545827602166,
      "meta": {
        "source": "arbocensus",
        "id": 1067
      }
    },
    {
      "lat": -33.438364058906025,
      "lng": -70.54567150994862,
      "meta": {
        "source": "arbocensus",
        "id": 1069
      }
    },
    {
      "lat": -33.438846585669395,
      "lng": -70.5460233209046,
      "meta": {
        "source": "arbocensus",
        "id": 1070
      }
    },
    {
      "lat": -33.43885236125939,
      "lng": -70.54604719886616,
      "meta": {
        "source": "arbocensus",
        "id": 1072
      }
    },
    {
      "lat": -33.438670844537036,
      "lng": -70.54587824088584,
      "meta": {
        "source": "arbocensus",
        "id": 1071
      }
    },
    {
      "lat": -33.438834840907084,
      "lng": -70.54602975116119,
      "meta": {
        "source": "arbocensus",
        "id": 1075
      }
    },
    {
      "lat": -33.43873585994764,
      "lng": -70.545885193933,
      "meta": {
        "source": "arbocensus",
        "id": 1076
      }
    },
    {
      "lat": -33.43892722186957,
      "lng": -70.54608246787159,
      "meta": {
        "source": "arbocensus",
        "id": 1079
      }
    },
    {
      "lat": -33.43798212548464,
      "lng": -70.54556378620795,
      "meta": {
        "source": "arbocensus",
        "id": 1081
      }
    },
    {
      "lat": -33.44176819810169,
      "lng": -70.54336983904274,
      "meta": {
        "source": "arbocensus",
        "id": 1388
      }
    },
    {
      "lat": -33.44180768005298,
      "lng": -70.543495349757,
      "meta": {
        "source": "arbocensus",
        "id": 1389
      }
    },
    {
      "lat": -33.44248093881682,
      "lng": -70.5434541219492,
      "meta": {
        "source": "arbocensus",
        "id": 1403
      }
    },
    {
      "lat": -33.442408385033595,
      "lng": -70.54340029413763,
      "meta": {
        "source": "arbocensus",
        "id": 1404
      }
    },
    {
      "lat": -33.442411133002395,
      "lng": -70.54341809541322,
      "meta": {
        "source": "arbocensus",
        "id": 1408
      }
    },
    {
      "lat": -33.44219978320894,
      "lng": -70.54339787038994,
      "meta": {
        "source": "arbocensus",
        "id": 1411
      }
    },
    {
      "lat": -33.44241650557877,
      "lng": -70.54324371520472,
      "meta": {
        "source": "arbocensus",
        "id": 1421
      }
    },
    {
      "lat": -33.44241642557256,
      "lng": -70.54325097391704,
      "meta": {
        "source": "arbocensus",
        "id": 1425
      }
    },
    {
      "lat": -33.44242860665054,
      "lng": -70.54326773073842,
      "meta": {
        "source": "arbocensus",
        "id": 1428
      }
    },
    {
      "lat": -33.44255454192368,
      "lng": -70.54301173879028,
      "meta": {
        "source": "arbocensus",
        "id": 1429
      }
    },
    {
      "lat": -33.442925488975625,
      "lng": -70.54327148718154,
      "meta": {
        "source": "arbocensus",
        "id": 1437
      }
    },
    {
      "lat": -33.44355180472632,
      "lng": -70.54329808921254,
      "meta": {
        "source": "arbocensus",
        "id": 1452
      }
    },
    {
      "lat": -33.443063342229145,
      "lng": -70.54339534971112,
      "meta": {
        "source": "arbocensus",
        "id": 1454
      }
    },
    {
      "lat": -33.44259796492436,
      "lng": -70.54395432957449,
      "meta": {
        "source": "arbocensus",
        "id": 1458
      }
    },
    {
      "lat": -33.44322516142975,
      "lng": -70.54338588977856,
      "meta": {
        "source": "arbocensus",
        "id": 1459
      }
    },
    {
      "lat": -33.443983979504196,
      "lng": -70.5433815298036,
      "meta": {
        "source": "arbocensus",
        "id": 1460
      }
    },
    {
      "lat": -33.44273112381083,
      "lng": -70.5433170305686,
      "meta": {
        "source": "arbocensus",
        "id": 1461
      }
    },
    {
      "lat": -33.43684562447618,
      "lng": -70.54660403670728,
      "meta": {
        "source": "arbocensus",
        "id": 1629
      }
    },
    {
      "lat": -33.43691390274224,
      "lng": -70.54302939699149,
      "meta": {
        "source": "arbocensus",
        "id": 1579
      }
    },
    {
      "lat": -33.43637275998814,
      "lng": -70.5465002441773,
      "meta": {
        "source": "arbocensus",
        "id": 1601
      }
    },
    {
      "lat": -33.436974037076176,
      "lng": -70.54661277262605,
      "meta": {
        "source": "arbocensus",
        "id": 1634
      }
    },
    {
      "lat": -33.4370224710708,
      "lng": -70.54650547144912,
      "meta": {
        "source": "arbocensus",
        "id": 1645
      }
    },
    {
      "lat": -33.43682492173721,
      "lng": -70.54647226832763,
      "meta": {
        "source": "arbocensus",
        "id": 1638
      }
    },
    {
      "lat": -33.437018589617516,
      "lng": -70.54663565151469,
      "meta": {
        "source": "arbocensus",
        "id": 1650
      }
    },
    {
      "lat": -33.434732491326876,
      "lng": -70.54808796002474,
      "meta": {
        "source": "arbocensus",
        "id": 1677
      }
    },
    {
      "lat": -33.434559848925986,
      "lng": -70.54838105466234,
      "meta": {
        "source": "arbocensus",
        "id": 1696
      }
    },
    {
      "lat": -33.434407787966066,
      "lng": -70.54699735964999,
      "meta": {
        "source": "arbocensus",
        "id": 1698
      }
    },
    {
      "lat": -33.438732166458436,
      "lng": -70.54565503169697,
      "meta": {
        "source": "arbocensus",
        "id": 1080
      }
    },
    {
      "lat": -33.43802579735412,
      "lng": -70.54565556969281,
      "meta": {
        "source": "arbocensus",
        "id": 1083
      }
    },
    {
      "lat": -33.43818166688147,
      "lng": -70.54424858254355,
      "meta": {
        "source": "arbocensus",
        "id": 1120
      }
    },
    {
      "lat": -33.43786757019081,
      "lng": -70.54562166536991,
      "meta": {
        "source": "arbocensus",
        "id": 1082
      }
    },
    {
      "lat": -33.43809317413029,
      "lng": -70.54425692554506,
      "meta": {
        "source": "arbocensus",
        "id": 1119
      }
    },
    {
      "lat": -33.43786705835768,
      "lng": -70.54565766732871,
      "meta": {
        "source": "arbocensus",
        "id": 1085
      }
    },
    {
      "lat": -33.438003569068385,
      "lng": -70.54556965403616,
      "meta": {
        "source": "arbocensus",
        "id": 1084
      }
    },
    {
      "lat": -33.43816643087081,
      "lng": -70.54554994483556,
      "meta": {
        "source": "arbocensus",
        "id": 1087
      }
    },
    {
      "lat": -33.438006317937884,
      "lng": -70.54514095384792,
      "meta": {
        "source": "arbocensus",
        "id": 1088
      }
    },
    {
      "lat": -33.437993674514416,
      "lng": -70.54551525743116,
      "meta": {
        "source": "arbocensus",
        "id": 1086
      }
    },
    {
      "lat": -33.43801430571445,
      "lng": -70.54525334085261,
      "meta": {
        "source": "arbocensus",
        "id": 1090
      }
    },
    {
      "lat": -33.43798915803885,
      "lng": -70.54540469241391,
      "meta": {
        "source": "arbocensus",
        "id": 1089
      }
    },
    {
      "lat": -33.43754713972782,
      "lng": -70.54747125859544,
      "meta": {
        "source": "arbocensus",
        "id": 1162
      }
    },
    {
      "lat": -33.4380929868498,
      "lng": -70.54527647883549,
      "meta": {
        "source": "arbocensus",
        "id": 1091
      }
    },
    {
      "lat": -33.43792121861308,
      "lng": -70.5454008574348,
      "meta": {
        "source": "arbocensus",
        "id": 1092
      }
    },
    {
      "lat": -33.43792659795976,
      "lng": -70.54502645919356,
      "meta": {
        "source": "arbocensus",
        "id": 1121
      }
    },
    {
      "lat": -33.437993419962595,
      "lng": -70.54498721493418,
      "meta": {
        "source": "arbocensus",
        "id": 1094
      }
    },
    {
      "lat": -33.43813110735121,
      "lng": -70.5450026460455,
      "meta": {
        "source": "arbocensus",
        "id": 1093
      }
    },
    {
      "lat": -33.437948777012,
      "lng": -70.54526799932428,
      "meta": {
        "source": "arbocensus",
        "id": 1095
      }
    },
    {
      "lat": -33.438098861625825,
      "lng": -70.54424017391398,
      "meta": {
        "source": "arbocensus",
        "id": 1122
      }
    },
    {
      "lat": -33.43813240512375,
      "lng": -70.54476915613486,
      "meta": {
        "source": "arbocensus",
        "id": 1097
      }
    },
    {
      "lat": -33.438088364577496,
      "lng": -70.54491609171295,
      "meta": {
        "source": "arbocensus",
        "id": 1096
      }
    },
    {
      "lat": -33.43764422370895,
      "lng": -70.54696014415346,
      "meta": {
        "source": "arbocensus",
        "id": 1153
      }
    },
    {
      "lat": -33.43806641866884,
      "lng": -70.54466811417016,
      "meta": {
        "source": "arbocensus",
        "id": 1098
      }
    },
    {
      "lat": -33.43795327779451,
      "lng": -70.54547382264761,
      "meta": {
        "source": "arbocensus",
        "id": 1141
      }
    },
    {
      "lat": -33.43812422466916,
      "lng": -70.54457300958425,
      "meta": {
        "source": "arbocensus",
        "id": 1099
      }
    },
    {
      "lat": -33.43810201133795,
      "lng": -70.54471572610305,
      "meta": {
        "source": "arbocensus",
        "id": 1100
      }
    },
    {
      "lat": -33.438095598214616,
      "lng": -70.54421323571162,
      "meta": {
        "source": "arbocensus",
        "id": 1123
      }
    },
    {
      "lat": -33.438247344629815,
      "lng": -70.5441843456796,
      "meta": {
        "source": "arbocensus",
        "id": 1101
      }
    },
    {
      "lat": -33.43805099373109,
      "lng": -70.54471025977332,
      "meta": {
        "source": "arbocensus",
        "id": 1102
      }
    },
    {
      "lat": -33.437847655346985,
      "lng": -70.545708524218,
      "meta": {
        "source": "arbocensus",
        "id": 1140
      }
    },
    {
      "lat": -33.437919726579594,
      "lng": -70.54504349680647,
      "meta": {
        "source": "arbocensus",
        "id": 1124
      }
    },
    {
      "lat": -33.43834850890126,
      "lng": -70.54341956467691,
      "meta": {
        "source": "arbocensus",
        "id": 1103
      }
    },
    {
      "lat": -33.43837989688466,
      "lng": -70.54357106196673,
      "meta": {
        "source": "arbocensus",
        "id": 1104
      }
    },
    {
      "lat": -33.43791659935084,
      "lng": -70.54517221622207,
      "meta": {
        "source": "arbocensus",
        "id": 1125
      }
    },
    {
      "lat": -33.43839364518407,
      "lng": -70.54354544678502,
      "meta": {
        "source": "arbocensus",
        "id": 1107
      }
    },
    {
      "lat": -33.43837726807939,
      "lng": -70.54323179215118,
      "meta": {
        "source": "arbocensus",
        "id": 1108
      }
    },
    {
      "lat": -33.43838166801688,
      "lng": -70.54332578831517,
      "meta": {
        "source": "arbocensus",
        "id": 1109
      }
    },
    {
      "lat": -33.43788836648594,
      "lng": -70.54556928055158,
      "meta": {
        "source": "arbocensus",
        "id": 1126
      }
    },
    {
      "lat": -33.438217842093074,
      "lng": -70.54311489196301,
      "meta": {
        "source": "arbocensus",
        "id": 1110
      }
    },
    {
      "lat": -33.438265678469584,
      "lng": -70.54323813500665,
      "meta": {
        "source": "arbocensus",
        "id": 1111
      }
    },
    {
      "lat": -33.43847027672796,
      "lng": -70.54318280930839,
      "meta": {
        "source": "arbocensus",
        "id": 1112
      }
    },
    {
      "lat": -33.438461285137095,
      "lng": -70.5430532900039,
      "meta": {
        "source": "arbocensus",
        "id": 1113
      }
    },
    {
      "lat": -33.43786051613121,
      "lng": -70.54552021193369,
      "meta": {
        "source": "arbocensus",
        "id": 1127
      }
    },
    {
      "lat": -33.438223960603516,
      "lng": -70.54342737538322,
      "meta": {
        "source": "arbocensus",
        "id": 1115
      }
    },
    {
      "lat": -33.438418692746176,
      "lng": -70.54360121002907,
      "meta": {
        "source": "arbocensus",
        "id": 1114
      }
    },
    {
      "lat": -33.438167546634865,
      "lng": -70.543723529175,
      "meta": {
        "source": "arbocensus",
        "id": 1116
      }
    },
    {
      "lat": -33.43793479532791,
      "lng": -70.54556644925778,
      "meta": {
        "source": "arbocensus",
        "id": 1128
      }
    },
    {
      "lat": -33.438112715509384,
      "lng": -70.5441834294767,
      "meta": {
        "source": "arbocensus",
        "id": 1118
      }
    },
    {
      "lat": -33.438238448675335,
      "lng": -70.54428082852925,
      "meta": {
        "source": "arbocensus",
        "id": 1117
      }
    },
    {
      "lat": -33.43782512863405,
      "lng": -70.54597015211269,
      "meta": {
        "source": "arbocensus",
        "id": 1143
      }
    },
    {
      "lat": -33.437880904155826,
      "lng": -70.54565103370064,
      "meta": {
        "source": "arbocensus",
        "id": 1129
      }
    },
    {
      "lat": -33.43791556578363,
      "lng": -70.54585776646631,
      "meta": {
        "source": "arbocensus",
        "id": 1142
      }
    },
    {
      "lat": -33.43794259469456,
      "lng": -70.54551164295518,
      "meta": {
        "source": "arbocensus",
        "id": 1130
      }
    },
    {
      "lat": -33.43787322971425,
      "lng": -70.54555516867865,
      "meta": {
        "source": "arbocensus",
        "id": 1131
      }
    },
    {
      "lat": -33.43786263966479,
      "lng": -70.54551820333305,
      "meta": {
        "source": "arbocensus",
        "id": 1132
      }
    },
    {
      "lat": -33.437671629990696,
      "lng": -70.54679635256592,
      "meta": {
        "source": "arbocensus",
        "id": 1152
      }
    },
    {
      "lat": -33.43785576140766,
      "lng": -70.54575938798062,
      "meta": {
        "source": "arbocensus",
        "id": 1133
      }
    },
    {
      "lat": -33.43800418814457,
      "lng": -70.54554162737774,
      "meta": {
        "source": "arbocensus",
        "id": 1134
      }
    },
    {
      "lat": -33.43781557567175,
      "lng": -70.5459391439834,
      "meta": {
        "source": "arbocensus",
        "id": 1145
      }
    },
    {
      "lat": -33.43789653132673,
      "lng": -70.54564504217761,
      "meta": {
        "source": "arbocensus",
        "id": 1136
      }
    },
    {
      "lat": -33.43792938635723,
      "lng": -70.54582106724025,
      "meta": {
        "source": "arbocensus",
        "id": 1144
      }
    },
    {
      "lat": -33.43783942265391,
      "lng": -70.54581668044335,
      "meta": {
        "source": "arbocensus",
        "id": 1135
      }
    },
    {
      "lat": -33.43796226610278,
      "lng": -70.5455056014277,
      "meta": {
        "source": "arbocensus",
        "id": 1137
      }
    },
    {
      "lat": -33.43785485014554,
      "lng": -70.54569635227661,
      "meta": {
        "source": "arbocensus",
        "id": 1138
      }
    },
    {
      "lat": -33.43790905714569,
      "lng": -70.54555158849952,
      "meta": {
        "source": "arbocensus",
        "id": 1139
      }
    },
    {
      "lat": -33.43759956074617,
      "lng": -70.54712414704852,
      "meta": {
        "source": "arbocensus",
        "id": 1154
      }
    },
    {
      "lat": -33.43777191544334,
      "lng": -70.54611977595488,
      "meta": {
        "source": "arbocensus",
        "id": 1146
      }
    },
    {
      "lat": -33.437905656295136,
      "lng": -70.54616744680675,
      "meta": {
        "source": "arbocensus",
        "id": 1147
      }
    },
    {
      "lat": -33.43770651947429,
      "lng": -70.54704167101423,
      "meta": {
        "source": "arbocensus",
        "id": 1155
      }
    },
    {
      "lat": -33.43776689621547,
      "lng": -70.54634134623464,
      "meta": {
        "source": "arbocensus",
        "id": 1148
      }
    },
    {
      "lat": -33.43779826172086,
      "lng": -70.54634929517665,
      "meta": {
        "source": "arbocensus",
        "id": 1149
      }
    },
    {
      "lat": -33.43776094468458,
      "lng": -70.54652343925459,
      "meta": {
        "source": "arbocensus",
        "id": 1150
      }
    }
  ]
}